{
  "generator-jhipster": {
    "applicationType": "microservice",
    "gitHubOrganization": "yathiraju",
    "baseName": "hotelroomservice",
    "packageName": "com.hotel.room.application",
    "serverPort": 8081,
    "serviceDiscoveryType": "eureka",
    "authenticationType": "jwt",
    "uaaBaseName": "../uaa",
    "cacheProvider": "hazelcast",
    "enableHibernateCache": true,
    "websocket": false,
    "databaseType": "sql",
    "devDatabaseType": "h2Disk",
    "prodDatabaseType": "mysql",
    "searchEngine": "elasticsearch",
    "enableSwaggerCodegen": false,
    "messageBroker": false,
    "buildTool": "gradle",
    "enableSocialSignIn": false,
    "useSass": true,
    "clientPackageManager": "yarn",
    "testFrameworks": [],
    "enableTranslation": false,
    "nativeLanguage": "en",
    "languages": [
      "en"
    ],
    "clientFramework": "angularX",
    "jhipsterVersion": "4.14.0",
    "packageFolder": "com/hotel/room/application",
    "jwtSecretKey": "aa24d3fc8430cbc8760c6c9cb5ef211f688d3519",
    "jhiPrefix": "jhi",
    "skipClient": true,
    "skipUserManagement": true
  }
}